ai_logger/__init__.py
ai_logger/src/__init__.py
ai_logger/src/__main__.py
ai_logger/src/example.py
ai_logger/src/user_interface/__init__.py
ai_logger/src/user_interface/uiux.py
ai_logger/src/utils/__init__.py
ai_logger/src/utils/ai_logger.json
ai_logger/src/utils/ai_logger.py
ai_logger/src/utils/config.py
ai_logger/src/utils/logger_tools.py
ai_logger/src/utils/models.py
ai_logger-0.1.2.dist-info/METADATA
ai_logger-0.1.2.dist-info/WHEEL
ai_logger-0.1.2.dist-info/entry_points.txt
ai_logger-0.1.2.dist-info/RECORD
