Metadata-Version: 2.3
Name: ai-logger
Version: 0.1.2
Summary: A module to add logging in json format that an AI could easily understand.
License: MIT
Author: VinnyVanGogh
Author-email: 133192356+VinnyVanGogh@users.noreply.github.com
Requires-Python: >=3.11,<4.0
Classifier: License :: OSI Approved :: MIT License
Classifier: Programming Language :: Python :: 3
Classifier: Programming Language :: Python :: 3.11
Classifier: Programming Language :: Python :: 3.12
Classifier: Programming Language :: Python :: 3.13
Requires-Dist: click (>=8.1.7,<9.0.0)
Requires-Dist: pydantic (>=2.11.3,<3.0.0)
Requires-Dist: pyperclip (>=1.9.0,<2.0.0)
Requires-Dist: python-dotenv (>=1.1.0,<2.0.0)
Requires-Dist: rich (>=14.0.0,<15.0.0)
